merquery/__init__.py
merquery/__version__.py
merquery/core.py
merquery-0.4.0.dist-info/DESCRIPTION.rst
merquery-0.4.0.dist-info/METADATA
merquery-0.4.0.dist-info/RECORD
merquery-0.4.0.dist-info/WHEEL
merquery-0.4.0.dist-info/metadata.json
merquery-0.4.0.dist-info/top_level.txt
