Metadata-Version: 2.0
Name: merquery
Version: 0.4.0
Summary: UNOFFICIAL Mercari(jp) item search query builder
Home-page: https://github.com/upamune/merquery
Author: Yu SERIZAWA
Author-email: info@serizawa.me
License: MIT
Platform: UNKNOWN
Classifier: License :: OSI Approved :: MIT License
Classifier: Programming Language :: Python
Classifier: Programming Language :: Python :: 3.5
Classifier: Programming Language :: Python :: 3.6
